boxjoin/__init__.py
boxjoin/core.py
boxjoin-0.3.3.dist-info/licenses/LICENSE
boxjoin-0.3.3.dist-info/METADATA
boxjoin-0.3.3.dist-info/WHEEL
boxjoin-0.3.3.dist-info/top_level.txt
boxjoin-0.3.3.dist-info/RECORD
